pyjsparser/__init__.py
pyjsparser/parser.py
pyjsparser/pyjsparserdata.py
pyjsparser/std_nodes.py
pyjsparser-2.7.0.dist-info/LICENSE
pyjsparser-2.7.0.dist-info/METADATA
pyjsparser-2.7.0.dist-info/WHEEL
pyjsparser-2.7.0.dist-info/top_level.txt
pyjsparser-2.7.0.dist-info/RECORD
